mineru/__init__.py
mineru/version.py
mineru/backend/__init__.py
mineru/backend/utils.py
mineru/backend/hybrid/__init__.py
mineru/backend/hybrid/hybrid_analyze.py
mineru/backend/hybrid/hybrid_magic_model.py
mineru/backend/hybrid/hybrid_model_output_to_middle_json.py
mineru/backend/pipeline/__init__.py
mineru/backend/pipeline/batch_analyze.py
mineru/backend/pipeline/model_init.py
mineru/backend/pipeline/model_json_to_middle_json.py
mineru/backend/pipeline/model_list.py
mineru/backend/pipeline/para_split.py
mineru/backend/pipeline/pipeline_analyze.py
mineru/backend/pipeline/pipeline_magic_model.py
mineru/backend/pipeline/pipeline_middle_json_mkcontent.py
mineru/backend/vlm/__init__.py
mineru/backend/vlm/model_output_to_middle_json.py
mineru/backend/vlm/utils.py
mineru/backend/vlm/vlm_analyze.py
mineru/backend/vlm/vlm_magic_model.py
mineru/backend/vlm/vlm_middle_json_mkcontent.py
mineru/cli/__init__.py
mineru/cli/client.py
mineru/cli/common.py
mineru/cli/fast_api.py
mineru/cli/gradio_app.py
mineru/cli/models_download.py
mineru/cli/vlm_server.py
mineru/data/__init__.py
mineru/data/data_reader_writer/__init__.py
mineru/data/data_reader_writer/base.py
mineru/data/data_reader_writer/dummy.py
mineru/data/data_reader_writer/filebase.py
mineru/data/data_reader_writer/multi_bucket_s3.py
mineru/data/data_reader_writer/s3.py
mineru/data/io/__init__.py
mineru/data/io/base.py
mineru/data/io/http.py
mineru/data/io/s3.py
mineru/data/utils/__init__.py
mineru/data/utils/exceptions.py
mineru/data/utils/path_utils.py
mineru/data/utils/schemas.py
mineru/model/__init__.py
mineru/model/layout/__init__.py
mineru/model/layout/doclayoutyolo.py
mineru/model/mfd/__init__.py
mineru/model/mfd/yolo_v8.py
mineru/model/mfr/__init__.py
mineru/model/mfr/utils.py
mineru/model/mfr/pp_formulanet_plus_m/__init__.py
mineru/model/mfr/pp_formulanet_plus_m/predict_formula.py
mineru/model/mfr/pp_formulanet_plus_m/processors.py
mineru/model/mfr/unimernet/Unimernet.py
mineru/model/mfr/unimernet/__init__.py
mineru-2.7.4.dist-info/licenses/LICENSE.md
mineru-2.7.4.dist-info/METADATA
mineru-2.7.4.dist-info/WHEEL
mineru-2.7.4.dist-info/entry_points.txt
mineru-2.7.4.dist-info/top_level.txt
mineru-2.7.4.dist-info/RECORD
