Metadata-Version: 2.4
Name: mineru
Version: 2.7.4
Summary: A practical tool for converting PDF to Markdown
License: AGPL-3.0
Project-URL: homepage, https://mineru.net/
Project-URL: documentation, https://opendatalab.github.io/MinerU/
Project-URL: repository, https://github.com/opendatalab/MinerU
Project-URL: issues, https://github.com/opendatalab/MinerU/issues
Keywords: magic-pdf,mineru,MinerU,convert,pdf,markdown
Classifier: Programming Language :: Python :: 3.10
Classifier: Programming Language :: Python :: 3.11
Classifier: Programming Language :: Python :: 3.12
Classifier: Programming Language :: Python :: 3.13
Requires-Python: <3.14,>=3.10
License-File: LICENSE.md
Requires-Dist: boto3>=1.28.43
Requires-Dist: click>=8.1.7
Requires-Dist: loguru>=0.7.2
Requires-Dist: numpy>=1.21.6
Requires-Dist: pdfminer.six>=20251230
Requires-Dist: tqdm>=4.67.1
Requires-Dist: requests
Requires-Dist: httpx
Requires-Dist: pillow>=11.0.0
Requires-Dist: pypdfium2>=4.30.0
Requires-Dist: pypdf>=5.6.0
Requires-Dist: reportlab
Requires-Dist: pdftext>=0.6.3
Requires-Dist: modelscope>=1.26.0
Requires-Dist: huggingface-hub>=0.32.4
Requires-Dist: json-repair>=0.46.2
Requires-Dist: opencv-python>=4.11.0.86
Requires-Dist: fast-langdetect<0.3.0,>=0.2.3
Requires-Dist: scikit-image<1.0.0,>=0.25.0
Requires-Dist: openai<3,>=1.70.0
Requires-Dist: beautifulsoup4<5,>=4.13.5
Requires-Dist: magika<1.1.0,>=0.6.2
Requires-Dist: mineru-vl-utils<1,>=0.1.19.1
Requires-Dist: qwen-vl-utils<1,>=0.0.14
Provides-Extra: test
Requires-Dist: mineru[core]; extra == "test"
Requires-Dist: pytest; extra == "test"
Requires-Dist: pytest-cov; extra == "test"
Requires-Dist: coverage; extra == "test"
Requires-Dist: fuzzywuzzy; extra == "test"
Provides-Extra: vlm
Requires-Dist: torch<3,>=2.6.0; extra == "vlm"
Requires-Dist: transformers!=4.57.2,<5.0.0,>=4.51.1; extra == "vlm"
Requires-Dist: accelerate>=1.5.1; extra == "vlm"
Provides-Extra: vllm
Requires-Dist: vllm<0.12,>=0.10.1.1; extra == "vllm"
Provides-Extra: lmdeploy
Requires-Dist: lmdeploy<0.12,>=0.10.2; extra == "lmdeploy"
Provides-Extra: mlx
Requires-Dist: mlx-vlm<0.4,>=0.3.3; extra == "mlx"
Provides-Extra: pipeline
Requires-Dist: matplotlib<4,>=3.10; extra == "pipeline"
Requires-Dist: ultralytics<9,>=8.3.48; extra == "pipeline"
Requires-Dist: doclayout_yolo==0.0.4; extra == "pipeline"
Requires-Dist: dill<1,>=0.3.8; extra == "pipeline"
Requires-Dist: PyYAML<7,>=6.0.1; extra == "pipeline"
Requires-Dist: ftfy<7,>=6.3.1; extra == "pipeline"
Requires-Dist: shapely<3,>=2.0.7; extra == "pipeline"
Requires-Dist: pyclipper<2,>=1.3.0; extra == "pipeline"
Requires-Dist: omegaconf<3,>=2.3.0; extra == "pipeline"
Requires-Dist: torch<3,>=2.6.0; extra == "pipeline"
Requires-Dist: torchvision; extra == "pipeline"
Requires-Dist: transformers!=4.51.0,<5.0.0,>=4.49.0; extra == "pipeline"
Requires-Dist: onnxruntime>1.17.0; extra == "pipeline"
Provides-Extra: api
Requires-Dist: fastapi; extra == "api"
Requires-Dist: python-multipart; extra == "api"
Requires-Dist: uvicorn; extra == "api"
Provides-Extra: gradio
Requires-Dist: gradio==5.49.1; extra == "gradio"
Requires-Dist: gradio-pdf==0.0.22; extra == "gradio"
Provides-Extra: core
Requires-Dist: mineru[vlm]; extra == "core"
Requires-Dist: mineru[pipeline]; extra == "core"
Requires-Dist: mineru[api]; extra == "core"
Requires-Dist: mineru[gradio]; extra == "core"
Provides-Extra: all
Requires-Dist: mineru[core]; extra == "all"
Requires-Dist: mineru[mlx]; sys_platform == "darwin" and extra == "all"
Requires-Dist: mineru[vllm]; sys_platform == "linux" and extra == "all"
Requires-Dist: mineru[lmdeploy]; sys_platform == "windows" and extra == "all"
Dynamic: license-file
